regex4seq/__init__.py
regex4seq/regex4seq.py
regex4seq/trail.py
regex4seq-1.0.1.dist-info/LICENSE
regex4seq-1.0.1.dist-info/METADATA
regex4seq-1.0.1.dist-info/WHEEL
regex4seq-1.0.1.dist-info/RECORD
